odoo8_addon_web_listview_show_advanced_search-8.0.1.0.0-py2.7-nspkg.pth
odoo_addons/web_listview_show_advanced_search/__openerp__.py
odoo_addons/web_listview_show_advanced_search/__init__.py
odoo_addons/web_listview_show_advanced_search/README.rst
odoo_addons/web_listview_show_advanced_search/views/webclient_templates.xml
odoo_addons/web_listview_show_advanced_search/static/description/icon.png
odoo_addons/web_listview_show_advanced_search/static/src/js/web_listview_show_advanced_search.js
odoo8_addon_web_listview_show_advanced_search-8.0.1.0.0.dist-info/top_level.txt
odoo8_addon_web_listview_show_advanced_search-8.0.1.0.0.dist-info/WHEEL
odoo8_addon_web_listview_show_advanced_search-8.0.1.0.0.dist-info/RECORD
odoo8_addon_web_listview_show_advanced_search-8.0.1.0.0.dist-info/metadata.json
odoo8_addon_web_listview_show_advanced_search-8.0.1.0.0.dist-info/DESCRIPTION.rst
odoo8_addon_web_listview_show_advanced_search-8.0.1.0.0.dist-info/METADATA
odoo8_addon_web_listview_show_advanced_search-8.0.1.0.0.dist-info/namespace_packages.txt
